src/__init__.py
src/main.py
src/cli/__init__.py
src/cli/main.py
src/lib/__init__.py
src/lib/utils.py
src/models/__init__.py
src/models/todo.py
src/services/__init__.py
src/services/classifier.py
src/services/storage.py
todo_cli_nl-0.1.0.dist-info/METADATA
todo_cli_nl-0.1.0.dist-info/WHEEL
todo_cli_nl-0.1.0.dist-info/entry_points.txt
todo_cli_nl-0.1.0.dist-info/licenses/LICENSE
todo_cli_nl-0.1.0.dist-info/RECORD
