Metadata-Version: 2.4
Name: todo-cli-nl
Version: 0.1.0
Summary: A command-line todo list application with natural language input
Project-URL: Homepage, https://gitlab.com/roscom/todo
Project-URL: Repository, https://gitlab.com/roscom/todo
Project-URL: Issues, https://gitlab.com/roscom/todo/-/issues
Author: Ross Cameron
License: MIT License
License-File: LICENSE
Keywords: cli,natural-language,task-manager,todo
Classifier: Development Status :: 4 - Beta
Classifier: Environment :: Console
Classifier: Intended Audience :: End Users/Desktop
Classifier: License :: OSI Approved :: MIT License
Classifier: Operating System :: OS Independent
Classifier: Programming Language :: Python :: 3
Classifier: Programming Language :: Python :: 3.10
Classifier: Programming Language :: Python :: 3.11
Classifier: Programming Language :: Python :: 3.12
Classifier: Topic :: Utilities
Requires-Python: >=3.10
Requires-Dist: pydantic>=2.0
